{
  "937013272": [
    {
      "type": "Группа",
      "value": "ис-33"
    }
  ],
  "1160934050": [
    {
      "type": "Группа",
      "value": "ис-33"
    }
  ],
  "848265756": [
    {
      "type": "Группа",
      "value": "са-25"
    }
  ],
  "1075887343": [
    {
      "type": "Преподаватель",
      "value": "кошкина а.а."
    }
  ],
  "1298943231": [
    {
      "type": "Группа",
      "value": "ис-33"
    }
  ],
  "936966834": [
    {
      "type": "Группа",
      "value": "са-25"
    }
  ],
  "1211492678": [
    {
      "type": "Группа",
      "value": "са-25"
    }
  ],
  "1785109111": [
    {
      "type": "Группа",
      "value": "ис-33"
    }
  ],
  "1196567123": [
    {
      "type": "Группа",
      "value": "ис-13"
    }
  ],
  "1157932550": [
    {
      "type": "Группа",
      "value": "ис-13"
    }
  ],
  "1029668072": [
    {
      "type": "Группа",
      "value": "ис-41"
    }
  ],
  "842312909": [
    {
      "type": "Группа",
      "value": "ис-12"
    }
  ],
  "1156083132": [
    {
      "type": "Группа",
      "value": "ис-13"
    }
  ],
  "814920235": [
    {
      "type": "Группа",
      "value": "ис-33"
    }
  ],
  "5508027431": [
    {
      "type": "Группа",
      "value": "ис-11"
    }
  ],
  "1379351622": [
    {
      "type": "Группа",
      "value": "ис-23"
    }
  ],
  "1220719516": [
    {
      "type": "Группа",
      "value": "ис-11"
    }
  ],
  "1761781627": [
    {
      "type": "Группа",
      "value": "ис-11"
    }
  ],
  "1930182132": [
    {
      "type": "Кабинет",
      "value": "310"
    }
  ],
  "928844071": [
    {
      "type": "Группа",
      "value": "ис-26"
    }
  ],
  "803779924": [
    {
      "type": "Группа",
      "value": "ис-32"
    }
  ],
  "1828610112": [
    {
      "type": "Группа",
      "value": "ис-11"
    }
  ],
  "1059020738": [
    {
      "type": "Группа",
      "value": "са-25"
    }
  ],
  "5003643247": [
    {
      "type": "Группа",
      "value": "са-25"
    }
  ],
  "865896357": [
    {
      "type": "Группа",
      "value": "ис-24"
    }
  ],
  "1996267234": [
    {
      "type": "Группа",
      "value": "ис-32"
    }
  ],
  "365783265": [
    {
      "type": "Группа",
      "value": "ис-32"
    }
  ],
  "744577007": [
    {
      "type": "Группа",
      "value": "ис-32"
    }
  ],
  "1205630682": [
    {
      "type": "Группа",
      "value": "ис-24"
    }
  ],
  "1938214562": [
    {
      "type": "Группа",
      "value": "са-25"
    }
  ],
  "1096646491": [
    {
      "type": "Группа",
      "value": "ис-33"
    }
  ],
  "1077159304": [
    {
      "type": "Группа",
      "value": "ис-23"
    }
  ],
  "6182400105": [
    {
      "type": "Группа",
      "value": "ис-12"
    }
  ],
  "691428279": [
    {
      "type": "Группа",
      "value": "ис-33"
    }
  ],
  "840954653": [
    {
      "type": "Группа",
      "value": "ис-12"
    }
  ],
  "867798233": [
    {
      "type": "Группа",
      "value": "ис-33"
    }
  ],
  "1924896180": [
    {
      "type": "Группа",
      "value": "са-25"
    }
  ],
  "1152974914": [
    {
      "type": "Группа",
      "value": "ис-32"
    }
  ],
  "5397524288": [
    {
      "type": "Группа",
      "value": "са-25"
    }
  ],
  "923810241": [
    {
      "type": "Группа",
      "value": "ис-33"
    }
  ],
  "5250360114": [
    {
      "type": "Группа",
      "value": "са-25"
    }
  ],
  "1991916911": [
    {
      "type": "Кабинет",
      "value": "са-25"
    }
  ],
  "905993967": [
    {
      "type": "Группа",
      "value": "са-25"
    }
  ],
  "923733747": [
    {
      "type": "Группа",
      "value": "са-25"
    }
  ],
  "983563310": [
    {
      "type": "Группа",
      "value": "са-22"
    }
  ],
  "1287035104": [
    {
      "type": "Группа",
      "value": "ис-33"
    }
  ],
  "1934313904": [
    {
      "type": "Группа",
      "value": "ис-23"
    }
  ],
  "1056617855": [
    {
      "type": "Группа",
      "value": "ис-26"
    }
  ],
  "1026992882": [
    {
      "type": "Группа",
      "value": "ис-41"
    }
  ],
  "626243089": [
    {
      "type": "Группа",
      "value": "ис-33"
    }
  ],
  "6664586399": [
    {
      "type": "Группа",
      "value": "са-25"
    }
  ],
  "944374883": [
    {
      "type": "Группа",
      "value": "ис-33"
    }
  ],
  "1401292760": [
    {
      "type": "Группа",
      "value": "ис-12"
    }
  ],
  "5278392054": [
    {
      "type": "Группа",
      "value": "ис-11"
    }
  ],
  "1289777448": [
    {
      "type": "Группа",
      "value": "ис-12"
    }
  ],
  "976552789": [
    {
      "type": "Группа",
      "value": "ис-32"
    }
  ],
  "1944697682": [
    {
      "type": "Группа",
      "value": "ис-12"
    }
  ],
  "689948052": [
    {
      "type": "Группа",
      "value": "ис-32"
    }
  ],
  "5763947429": [
    {
      "type": "Группа",
      "value": "ис-23"
    }
  ],
  "1387060838": [
    {
      "type": "Группа",
      "value": "са-35"
    }
  ],
  "5113542475": [
    {
      "type": "Группа",
      "value": "ис-26"
    }
  ],
  "1130375834": [
    {
      "type": "Группа",
      "value": "ис-33"
    }
  ],
  "5151181707": [
    {
      "type": "Группа",
      "value": "са-25"
    }
  ],
  "1791569429": [
    {
      "type": "Группа",
      "value": "ис-22"
    }
  ],
  "5635621839": [
    {
      "type": "Группа",
      "value": "ис-35"
    }
  ],
  "5181665378": [
    {
      "type": "Группа",
      "value": "ис-23"
    }
  ],
  "5564216050": [
    {
      "type": "Группа",
      "value": "ис-21"
    }
  ],
  "614949681": [
    {
      "type": "Группа",
      "value": "покс-45w"
    }
  ],
  "6582064225": [
    {
      "type": "Группа",
      "value": "ис-23"
    }
  ],
  "681157201": [
    {
      "type": "Группа",
      "value": "ис-23"
    }
  ],
  "1306263720": [
    {
      "type": "Группа",
      "value": "ис-23"
    }
  ],
  "832591959": [
    {
      "type": "Группа",
      "value": "ис-33"
    }
  ],
  "5195194988": [
    {
      "type": "Группа",
      "value": "ис-23"
    }
  ],
  "912824014": [
    {
      "type": "Группа",
      "value": "ис-33"
    }
  ],
  "821892692": [
    {
      "type": "Группа",
      "value": "ис-33"
    }
  ],
  "864638578": [
    {
      "type": "Группа",
      "value": "са-25"
    }
  ],
  "1141192385": [
    {
      "type": "Преподаватель",
      "value": "сенькин"
    }
  ],
  "739631742": [
    {
      "type": "Преподаватель",
      "value": "швецов"
    }
  ],
  "558726623": [
    {
      "type": "Группа",
      "value": "са-25"
    }
  ],
  "1177975163": [
    {
      "type": "Группа",
      "value": "са-25"
    }
  ],
  "632803256": [
    {
      "type": "Группа",
      "value": "ис-33"
    }
  ],
  "1051882333": [
    {
      "type": "Группа",
      "value": "са-25"
    }
  ],
  "1291236979": [
    {
      "type": "Группа",
      "value": "са-25"
    }
  ],
  "1703347075": [
    {
      "type": "Группа",
      "value": "са-25"
    }
  ],
  "1838959895": [
    {
      "type": "Группа",
      "value": "ис-24"
    }
  ],
  "1864103069": [
    {
      "type": "Группа",
      "value": "ис-24"
    }
  ],
  "1031246139": [
    {
      "type": "Группа",
      "value": "са-26"
    }
  ],
  "2056315526": [
    {
      "type": "Группа",
      "value": "ис-24"
    }
  ],
  "1149541072": [
    {
      "type": "Группа",
      "value": "ис-26"
    }
  ],
  "980649205": [
    {
      "type": "Группа",
      "value": "са-25"
    }
  ],
  "1775884438": [
    {
      "type": "Группа",
      "value": "ис-12"
    }
  ],
  "589390791": [
    {
      "type": "Группа",
      "value": "са-25"
    }
  ],
  "5541632390": [
    {
      "type": "Группа",
      "value": "ис-12"
    }
  ],
  "907016478": [
    {
      "type": "Кабинет",
      "value": "/remove_pattern"
    }
  ],
  "424698209": [
    {
      "type": "Преподаватель",
      "value": "деева а.а"
    }
  ],
  "821651842": [
    {
      "type": "Группа",
      "value": "иба-34"
    }
  ],
  "1175725657": [
    {
      "type": "Группа",
      "value": "ис-26"
    }
  ],
  "528186138": [
    {
      "type": "Группа",
      "value": "ис-26"
    }
  ],
  "991728528": [
    {
      "type": "Группа",
      "value": "ис-34"
    }
  ],
  "5587085719": [
    {
      "type": "Группа",
      "value": "ис-34"
    }
  ],
  "1063601351": [
    {
      "type": "Группа",
      "value": "са-25"
    }
  ],
  "1028256024": [
    {
      "type": "Группа",
      "value": "ис-26"
    }
  ]
}